imagetochar
imagetochar.py
setup.py
./imagetochar
./imagetochar.py
image2char/README.md
image2char/__init__.py
image2char/input1.jpg
image2char/run.py
image2char/tool.py
image2char.egg-info/PKG-INFO
image2char.egg-info/SOURCES.txt
image2char.egg-info/dependency_links.txt
image2char.egg-info/requires.txt
image2char.egg-info/top_level.txt
image2char/core/__init__.py
image2char/core/processor.py
image2char/core/scanner.py