Metadata-Version: 2.1
Name: image2char
Version: 0.1.2
Summary: small tool to transfer image between cmd char
Home-page: https://github.com/cpak00/image2char
Author: cpak00
Author-email: cymcpak00@gmail.com
License: MIT Licence
Keywords: image,char,transfer,cmd,shell
Platform: any
